plexus/__init__.py
plexus/plexus.py
plexus-0.0.4.dist-info/DESCRIPTION.rst
plexus-0.0.4.dist-info/METADATA
plexus-0.0.4.dist-info/RECORD
plexus-0.0.4.dist-info/WHEEL
plexus-0.0.4.dist-info/metadata.json
plexus-0.0.4.dist-info/top_level.txt
