Metadata-Version: 2.0
Name: plexus
Version: 0.0.4
Summary: Plexus is exceptionally bio-inspired, a revolutionary approach to the artificial neural networks
Home-page: https://github.com/mertyildiran/Plexus
Author: Mehmet Mert Yildiran
Author-email: mert.yildiran@bil.omu.edu.tr
License: MIT
Keywords: artifical neural networks
Platform: UNKNOWN
Classifier: Development Status :: 3 - Alpha
Classifier: Intended Audience :: Developers
Classifier: Topic :: Scientific/Engineering :: Artificial Intelligence
Classifier: License :: OSI Approved :: MIT License
Classifier: Programming Language :: Python :: 2.7
